sendgrid_django-4.0.4.dist-info/DESCRIPTION.rst
sendgrid_django-4.0.4.dist-info/METADATA
sendgrid_django-4.0.4.dist-info/RECORD
sendgrid_django-4.0.4.dist-info/WHEEL
sendgrid_django-4.0.4.dist-info/metadata.json
sendgrid_django-4.0.4.dist-info/top_level.txt
sgbackend/__init__.py
sgbackend/mail.py
sgbackend/version.py
