Metadata-Version: 2.0
Name: sendgrid-django
Version: 4.0.4
Summary: SendGrid Backend for Django
Home-page: https://github.com/elbuo8/sendgrid-django
Author: Yamil Asusta
Author-email: yamil@sendgrid.com
License: MIT
Platform: UNKNOWN
Requires-Dist: sendgrid (<4,>=3.5)
